yycli/README.md
yycli/__init__.py
yycli/__main__.py
yycli/config.py
yycli/tests.py
yycli/commands/__init__.py
yycli/commands/confuse.py
yycli/commands/crypt.py
yycli/commands/ipinfo.py
yycli/commands/weather/__init__.py
yycli/commands/weather/backends/amap.py
yycli/commands/weather/backends/baidu.py
yycli/commands/weather/backends/qweather.py
yycli/commands/weather/backends/seniverse.py
yycli/conf/config.toml
yycli-0.0.12.dist-info/licenses/LICENSE
yycli-0.0.12.dist-info/METADATA
yycli-0.0.12.dist-info/WHEEL
yycli-0.0.12.dist-info/entry_points.txt
yycli-0.0.12.dist-info/top_level.txt
yycli-0.0.12.dist-info/RECORD
