Metadata-Version: 2.4
Name: yycli
Version: 0.0.12
Summary: tools for routine work
Author-email: Pride Leong <lykling.lyk@gmail.com>
Project-URL: Homepage, https://github.com/lykling/comet/tree/main/yycli
Project-URL: Bug Tracker, https://github.com/lykling/comet/issues
Requires-Python: >=3.11
License-File: LICENSE
Requires-Dist: pycryptodome
Requires-Dist: setuptools
Requires-Dist: geoip2
Requires-Dist: requests
Requires-Dist: openpyxl
Requires-Dist: ipip-ipdb
Requires-Dist: xlrd
Requires-Dist: PyJWT[crypto]
Dynamic: license-file
